LICENSE
README.rst
setup.py
match/Match.py
match/__init__.py
match.egg-info/PKG-INFO
match.egg-info/SOURCES.txt
match.egg-info/dependency_links.txt
match.egg-info/requires.txt
match.egg-info/top_level.txt