Metadata-Version: 2.1
Name: match
Version: 0.3.1
Summary: Match tokenized words and phrases within the original, untokenized, often messy, text.
Home-page: https://github.com/EducationalTestingService/match
Author: Diane Napolitano
Author-email: dmnapolitano@gmail.com
Keywords: tokenization
Classifier: License :: OSI Approved :: Apache Software License
Classifier: Topic :: Text Processing
Classifier: Programming Language :: Python
Classifier: Operating System :: Microsoft :: Windows
Classifier: Operating System :: POSIX
Classifier: Operating System :: Unix
Classifier: Operating System :: MacOS
Classifier: Programming Language :: Python :: 3
Classifier: Programming Language :: Python :: 3.8
Classifier: Programming Language :: Python :: 3.9
License-File: LICENSE
